Workbook

Sheet Инструкция
A1: Auron Finance — ежедневный учёт (Way Market)
A3: Что это | B3: Рабочая тетрадь магазина. Заполняется каждый день. Считает всё само по формулам приложения.
A4: Сначала — один раз | B4: Лист «Справочники»: впиши поставщиков с начальными долгами, сотрудников со ставками, статьи накоплений, отделы, целевую рентабельность.
A5: Каждое утро | B5: Лист «Касса»: вводи Z-отчёт по сменам. Расхождение посчитается само.
A6: В течение дня | B6: Лист «Выплаты» — оплаты и накладные поставщикам. Лист «Заказы» — что заказали и что пришло.
A7: Каждый день | B7: Лист «Табель» — кто работал. Лист «Накопления» — сколько отложил на аренду/зарплату/налоги.
A8: Долги | B8: Лист «Долги» считает текущий долг каждого поставщика сам из листа «Выплаты».
A9: Зарплата | B9: Лист «Зарплата» считает к выплате: ставка × отработано − авансы.
A10: Итог месяца | B10: Лист «Отчёт» собирает выручку, расходы, прибыль и рентабельность за месяц.
A12: ФОРМУЛЫ (как в приложении)
A13: Расхождение кассы | B13: (Фактическая наличка + Выплаты с кассы) − Z-отчёт по наличке. < 0 недостача · > 0 излишек · = 0 идеально.
A14: Долг поставщику | B14: Начальный долг + Накладные (взяли в долг) − Оплачено − Возвраты.
A15: Зарплата к выплате | B15: Ставка × Отработано (дней/часов) − Авансы.
A16: Откладывать в день | B16: (План статьи − Уже отложено) / Дней до конца месяца.
A17: Рентабельность | B17: (Выручка − Себестоимость) / Выручка × 100%.
A18: Свободно | B18: Наличка в кассе − плановые выплаты − резервы накоплений.

Sheet Справочники
A1: Справочники — заполнить один раз
A2: Имена отсюда подставляются в выпадающих списках на других листах. Можно добавлять строки.
A4: Поставщик | B4: Телефон | C4: Начальный долг | E4: Сотрудник | F4: Должность | G4: Оплата (день/час) | H4: Ставка | J4: Статья накоплений | K4: План в месяц | M4: Отделы | O4: Настройки
A5: ООО Альфа | B5: +7 900 000-00-01 | C5: 120000 | E5: Марина | F5: Бухгалтер | G5: день | H5: 2500 | J5: Аренда | K5: 60000 | M5: Молочка | O5: Целевая рентабельность | P5: 0.22
A6: Иванов П. | B6: +7 900 000-00-02 | C6: 45000 | E6: Олег | F6: Администратор | G6: день | H6: 2000 | J6: Зарплата | K6: 150000 | M6: Бакалея | O6: Метод накоплений | P6: виртуальный резерв
A7: Нурмат ИП | B7: +7 900 000-00-03 | C7: 0 | E7: Гуля | F7: Продавец | G7: день | H7: 1800 | J7: Налоги | K7: 40000 | M7: Заморозка | O7: Дней в месяце | P7: 30
J8: Коммуналка | K8: 15000 | M8: Химия
M9: Овощи

Sheet Касса
A1: Касса — Z-отчёт по сменам
A2: Расхождение = (Факт наличка + Выплаты с кассы) − Z наличка. Карта и СБП идут в банк, в расхождение по налу не входят.
A3: Дата | B3: Смена | C3: Кассир | D3: Z наличка | E3: Z карта | F3: Z СБП | G3: Выручка смены | H3: Факт наличка | I3: Выплаты с кассы | J3: Расхождение | K3: Статус | L3: Комментарий
G4: =D4+E4+F4 | J4: =H4+I4-D4 | K4: =IF(J4=0,"OK",IF(J4<0,"Недостача","Излишек"))
G5: =D5+E5+F5 | J5: =H5+I5-D5 | K5: =IF(J5=0,"OK",IF(J5<0,"Недостача","Излишек"))
G6: =D6+E6+F6 | J6: =H6+I6-D6 | K6: =IF(J6=0,"OK",IF(J6<0,"Недостача","Излишек"))
G7: =D7+E7+F7 | J7: =H7+I7-D7 | K7: =IF(J7=0,"OK",IF(J7<0,"Недостача","Излишек"))
G8: =D8+E8+F8 | J8: =H8+I8-D8 | K8: =IF(J8=0,"OK",IF(J8<0,"Недостача","Излишек"))
G9: =D9+E9+F9 | J9: =H9+I9-D9 | K9: =IF(J9=0,"OK",IF(J9<0,"Недостача","Излишек"))
G10: =D10+E10+F10 | J10: =H10+I10-D10 | K10: =IF(J10=0,"OK",IF(J10<0,"Недостача","Излишек"))
G11: =D11+E11+F11 | J11: =H11+I11-D11 | K11: =IF(J11=0,"OK",IF(J11<0,"Недостача","Излишек"))
G12: =D12+E12+F12 | J12: =H12+I12-D12 | K12: =IF(J12=0,"OK",IF(J12<0,"Недостача","Излишек"))
G13: =D13+E13+F13 | J13: =H13+I13-D13 | K13: =IF(J13=0,"OK",IF(J13<0,"Недостача","Излишек"))
G14: =D14+E14+F14 | J14: =H14+I14-D14 | K14: =IF(J14=0,"OK",IF(J14<0,"Недостача","Излишек"))
G15: =D15+E15+F15 | J15: =H15+I15-D15 | K15: =IF(J15=0,"OK",IF(J15<0,"Недостача","Излишек"))
... G203: =D203+E203+F203 | J203: =H203+I203-D203 | K203: =IF(J203=0,"OK",IF(J203<0,"Недостача","Излишек"))

Sheet Выплаты
A1: Выплаты и накладные поставщикам
A2: Вводи каждую операцию строкой. Лист «Долги» сам пересчитает текущий долг каждого поставщика.
A3: Дата | B3: Поставщик | C3: Оплачено наличными | D3: Новый долг (накладная) | E3: Возврат | F3: Комментарий

Sheet Долги
A1: Долги поставщикам — считается автоматически
A2: Текущий долг = Начальный + Накладные − Оплачено − Возвраты (из листа «Выплаты»).
A3: Поставщик | B3: Начальный долг | C3: Накладные | D3: Оплачено | E3: Текущий долг
A4: =IF(Справочники!A5="","",Справочники!A5) | B4: =IF(A4="","",Справочники!C5) | C4: =IF(A4="","",SUMIF(Выплаты!$B:$B,A4,Выплаты!$D:$D)) | D4: =IF(A4="","",SUMIF(Выплаты!$B:$B,A4,Выплаты!$C:$C)+SUMIF(Выплаты!$B:$B,A4,Выплаты!$E:$E)) | E4: =IF(A4="","",B4+C4-D4)
A5: =IF(Справочники!A6="","",Справочники!A6) | B5: =IF(A5="","",Справочники!C6) | C5: =IF(A5="","",SUMIF(Выплаты!$B:$B,A5,Выплаты!$D:$D)) | D5: =IF(A5="","",SUMIF(Выплаты!$B:$B,A5,Выплаты!$C:$C)+SUMIF(Выплаты!$B:$B,A5,Выплаты!$E:$E)) | E5: =IF(A5="","",B5+C5-D5)
A6: =IF(Справочники!A7="","",Справочники!A7) | B6: =IF(A6="","",Справочники!C7) | C6: =IF(A6="","",SUMIF(Выплаты!$B:$B,A6,Выплаты!$D:$D)) | D6: =IF(A6="","",SUMIF(Выплаты!$B:$B,A6,Выплаты!$C:$C)+SUMIF(Выплаты!$B:$B,A6,Выплаты!$E:$E)) | E6: =IF(A6="","",B6+C6-D6)
A7: =IF(Справочники!A8="","",Справочники!A8) | B7: =IF(A7="","",Справочники!C8) | C7: =IF(A7="","",SUMIF(Выплаты!$B:$B,A7,Выплаты!$D:$D)) | D7: =IF(A7="","",SUMIF(Выплаты!$B:$B,A7,Выплаты!$C:$C)+SUMIF(Выплаты!$B:$B,A7,Выплаты!$E:$E)) | E7: =IF(A7="","",B7+C7-D7)
A8: =IF(Справочники!A9="","",Справочники!A9) | B8: =IF(A8="","",Справочники!C9) | C8: =IF(A8="","",SUMIF(Выплаты!$B:$B,A8,Выплаты!$D:$D)) | D8: =IF(A8="","",SUMIF(Выплаты!$B:$B,A8,Выплаты!$C:$C)+SUMIF(Выплаты!$B:$B,A8,Выплаты!$E:$E)) | E8: =IF(A8="","",B8+C8-D8)
A9: =IF(Справочники!A10="","",Справочники!A10) | B9: =IF(A9="","",Справочники!C10) | C9: =IF(A9="","",SUMIF(Выплаты!$B:$B,A9,Выплаты!$D:$D)) | D9: =IF(A9="","",SUMIF(Выплаты!$B:$B,A9,Выплаты!$C:$C)+SUMIF(Выплаты!$B:$B,A9,Выплаты!$E:$E)) | E9: =IF(A9="","",B9+C9-D9)
A10: =IF(Справочники!A11="","",Справочники!A11) | B10: =IF(A10="","",Справочники!C11) | C10: =IF(A10="","",SUMIF(Выплаты!$B:$B,A10,Выплаты!$D:$D)) | D10: =IF(A10="","",SUMIF(Выплаты!$B:$B,A10,Выплаты!$C:$C)+SUMIF(Выплаты!$B:$B,A10,Выплаты!$E:$E)) | E10: =IF(A10="","",B10+C10-D10)
A11: =IF(Справочники!A12="","",Справочники!A12) | B11: =IF(A11="","",Справочники!C12) | C11: =IF(A11="","",SUMIF(Выплаты!$B:$B,A11,Выплаты!$D:$D)) | D11: =IF(A11="","",SUMIF(Выплаты!$B:$B,A11,Выплаты!$C:$C)+SUMIF(Выплаты!$B:$B,A11,Выплаты!$E:$E)) | E11: =IF(A11="","",B11+C11-D11)
A12: =IF(Справочники!A13="","",Справочники!A13) | B12: =IF(A12="","",Справочники!C13) | C12: =IF(A12="","",SUMIF(Выплаты!$B:$B,A12,Выплаты!$D:$D)) | D12: =IF(A12="","",SUMIF(Выплаты!$B:$B,A12,Выплаты!$C:$C)+SUMIF(Выплаты!$B:$B,A12,Выплаты!$E:$E)) | E12: =IF(A12="","",B12+C12-D12)
A13: =IF(Справочники!A14="","",Справочники!A14) | B13: =IF(A13="","",Справочники!C14) | C13: =IF(A13="","",SUMIF(Выплаты!$B:$B,A13,Выплаты!$D:$D)) | D13: =IF(A13="","",SUMIF(Выплаты!$B:$B,A13,Выплаты!$C:$C)+SUMIF(Выплаты!$B:$B,A13,Выплаты!$E:$E)) | E13: =IF(A13="","",B13+C13-D13)
A14: =IF(Справочники!A15="","",Справочники!A15) | B14: =IF(A14="","",Справочники!C15) | C14: =IF(A14="","",SUMIF(Выплаты!$B:$B,A14,Выплаты!$D:$D)) | D14: =IF(A14="","",SUMIF(Выплаты!$B:$B,A14,Выплаты!$C:$C)+SUMIF(Выплаты!$B:$B,A14,Выплаты!$E:$E)) | E14: =IF(A14="","",B14+C14-D14)
A15: =IF(Справочники!A16="","",Справочники!A16) | B15: =IF(A15="","",Справочники!C16) | C15: =IF(A15="","",SUMIF(Выплаты!$B:$B,A15,Выплаты!$D:$D)) | D15: =IF(A15="","",SUMIF(Выплаты!$B:$B,A15,Выплаты!$C:$C)+SUMIF(Выплаты!$B:$B,A15,Выплаты!$E:$E)) | E15: =IF(A15="","",B15+C15-D15)
... A53: =IF(Справочники!A54="","",Справочники!A54) | B53: =IF(A53="","",Справочники!C54) | C53: =IF(A53="","",SUMIF(Выплаты!$B:$B,A53,Выплаты!$D:$D)) | D53: =IF(A53="","",SUMIF(Выплаты!$B:$B,A53,Выплаты!$C:$C)+SUMIF(Выплаты!$B:$B,A53,Выплаты!$E:$E)) | E53: =IF(A53="","",B53+C53-D53)
A54: ИТОГО долг | E54: =SUM(E4:E53)

Sheet Заказы
A1: Заказы поставщикам
A2: Создал заказ — статус «Ожидается». Пришёл товар — поставь «Получен» и впиши фактическую сумму.
A3: Дата заказа | B3: Поставщик | C3: Отдел | D3: Сумма заказа | E3: Ожид. дата | F3: Статус | G3: Факт. сумма | H3: Дата прихода

Sheet Табель
A1: Табель — кто работал
A2: Коды: Р работал · П полдня · В выходной · Б больничный · О отпуск · Н прогул. Отработано считается само.
A3: Сотрудник | B3: 1 | C3: 2 | D3: 3 | E3: 4 | F3: 5 | G3: 6 | H3: 7 | I3: 8 | J3: 9 | K3: 10 | L3: 11 | M3: 12 | N3: 13 | O3: 14 | P3: 15 | Q3: 16 | R3: 17 | S3: 18 | T3: 19 | U3: 20 | V3: 21 | W3: 22 | X3: 23 | Y3: 24 | Z3: 25 | AA3: 26 | AB3: 27 | AC3: 28 | AD3: 29 | AE3: 30 | AF3: 31 | AG3: Отработано
A4: =IF(Справочники!E5="","",Справочники!E5) | AG4: =IF(A4="","",COUNTIF(B4:AF4,"Р")+0.5*COUNTIF(B4:AF4,"П"))
A5: =IF(Справочники!E6="","",Справочники!E6) | AG5: =IF(A5="","",COUNTIF(B5:AF5,"Р")+0.5*COUNTIF(B5:AF5,"П"))
A6: =IF(Справочники!E7="","",Справочники!E7) | AG6: =IF(A6="","",COUNTIF(B6:AF6,"Р")+0.5*COUNTIF(B6:AF6,"П"))
A7: =IF(Справочники!E8="","",Справочники!E8) | AG7: =IF(A7="","",COUNTIF(B7:AF7,"Р")+0.5*COUNTIF(B7:AF7,"П"))
A8: =IF(Справочники!E9="","",Справочники!E9) | AG8: =IF(A8="","",COUNTIF(B8:AF8,"Р")+0.5*COUNTIF(B8:AF8,"П"))
A9: =IF(Справочники!E10="","",Справочники!E10) | AG9: =IF(A9="","",COUNTIF(B9:AF9,"Р")+0.5*COUNTIF(B9:AF9,"П"))
A10: =IF(Справочники!E11="","",Справочники!E11) | AG10: =IF(A10="","",COUNTIF(B10:AF10,"Р")+0.5*COUNTIF(B10:AF10,"П"))
A11: =IF(Справочники!E12="","",Справочники!E12) | AG11: =IF(A11="","",COUNTIF(B11:AF11,"Р")+0.5*COUNTIF(B11:AF11,"П"))
A12: =IF(Справочники!E13="","",Справочники!E13) | AG12: =IF(A12="","",COUNTIF(B12:AF12,"Р")+0.5*COUNTIF(B12:AF12,"П"))
A13: =IF(Справочники!E14="","",Справочники!E14) | AG13: =IF(A13="","",COUNTIF(B13:AF13,"Р")+0.5*COUNTIF(B13:AF13,"П"))
A14: =IF(Справочники!E15="","",Справочники!E15) | AG14: =IF(A14="","",COUNTIF(B14:AF14,"Р")+0.5*COUNTIF(B14:AF14,"П"))
A15: =IF(Справочники!E16="","",Справочники!E16) | AG15: =IF(A15="","",COUNTIF(B15:AF15,"Р")+0.5*COUNTIF(B15:AF15,"П"))
... A33: =IF(Справочники!E34="","",Справочники!E34) | AG33: =IF(A33="","",COUNTIF(B33:AF33,"Р")+0.5*COUNTIF(B33:AF33,"П"))

Sheet Зарплата
A1: Зарплата за месяц
A2: К выплате = Ставка × Отработано − Авансы. Отработано берётся из листа «Табель».
A3: Сотрудник | B3: Ставка | C3: Отработано | D3: Начислено | E3: Авансы | F3: К выплате
A4: =IF(Справочники!E5="","",Справочники!E5) | B4: =IF(A4="","",Справочники!H5) | C4: =IF(A4="","",Табель!AG4) | D4: =IF(A4="","",B4*C4) | F4: =IF(A4="","",MAX(0,D4-E4))
A5: =IF(Справочники!E6="","",Справочники!E6) | B5: =IF(A5="","",Справочники!H6) | C5: =IF(A5="","",Табель!AG5) | D5: =IF(A5="","",B5*C5) | F5: =IF(A5="","",MAX(0,D5-E5))
A6: =IF(Справочники!E7="","",Справочники!E7) | B6: =IF(A6="","",Справочники!H7) | C6: =IF(A6="","",Табель!AG6) | D6: =IF(A6="","",B6*C6) | F6: =IF(A6="","",MAX(0,D6-E6))
A7: =IF(Справочники!E8="","",Справочники!E8) | B7: =IF(A7="","",Справочники!H8) | C7: =IF(A7="","",Табель!AG7) | D7: =IF(A7="","",B7*C7) | F7: =IF(A7="","",MAX(0,D7-E7))
A8: =IF(Справочники!E9="","",Справочники!E9) | B8: =IF(A8="","",Справочники!H9) | C8: =IF(A8="","",Табель!AG8) | D8: =IF(A8="","",B8*C8) | F8: =IF(A8="","",MAX(0,D8-E8))
A9: =IF(Справочники!E10="","",Справочники!E10) | B9: =IF(A9="","",Справочники!H10) | C9: =IF(A9="","",Табель!AG9) | D9: =IF(A9="","",B9*C9) | F9: =IF(A9="","",MAX(0,D9-E9))
A10: =IF(Справочники!E11="","",Справочники!E11) | B10: =IF(A10="","",Справочники!H11) | C10: =IF(A10="","",Табель!AG10) | D10: =IF(A10="","",B10*C10) | F10: =IF(A10="","",MAX(0,D10-E10))
A11: =IF(Справочники!E12="","",Справочники!E12) | B11: =IF(A11="","",Справочники!H12) | C11: =IF(A11="","",Табель!AG11) | D11: =IF(A11="","",B11*C11) | F11: =IF(A11="","",MAX(0,D11-E11))
A12: =IF(Справочники!E13="","",Справочники!E13) | B12: =IF(A12="","",Справочники!H13) | C12: =IF(A12="","",Табель!AG12) | D12: =IF(A12="","",B12*C12) | F12: =IF(A12="","",MAX(0,D12-E12))
A13: =IF(Справочники!E14="","",Справочники!E14) | B13: =IF(A13="","",Справочники!H14) | C13: =IF(A13="","",Табель!AG13) | D13: =IF(A13="","",B13*C13) | F13: =IF(A13="","",MAX(0,D13-E13))
A14: =IF(Справочники!E15="","",Справочники!E15) | B14: =IF(A14="","",Справочники!H15) | C14: =IF(A14="","",Табель!AG14) | D14: =IF(A14="","",B14*C14) | F14: =IF(A14="","",MAX(0,D14-E14))
A15: =IF(Справочники!E16="","",Справочники!E16) | B15: =IF(A15="","",Справочники!H16) | C15: =IF(A15="","",Табель!AG15) | D15: =IF(A15="","",B15*C15) | F15: =IF(A15="","",MAX(0,D15-E15))
... A33: =IF(Справочники!E34="","",Справочники!E34) | B33: =IF(A33="","",Справочники!H34) | C33: =IF(A33="","",Табель!AG33) | D33: =IF(A33="","",B33*C33) | F33: =IF(A33="","",MAX(0,D33-E33))
A34: ИТОГО к выплате | F34: =SUM(F4:F33)

Sheet Накопления
A1: Накопления на постоянные расходы
A2: Откладывать в день = (План − Отложено) / Дней до конца месяца. План берётся из «Справочников».
A3: Статья | B3: План в месяц | C3: Отложено | D3: Осталось | E3: Дней до конца | F3: В день
A4: =IF(Справочники!J5="","",Справочники!J5) | B4: =IF(A4="","",Справочники!K5) | D4: =IF(A4="","",B4-C4) | F4: =IF(OR(A4="",E4=0),"",MAX(0,D4)/E4)
A5: =IF(Справочники!J6="","",Справочники!J6) | B5: =IF(A5="","",Справочники!K6) | D5: =IF(A5="","",B5-C5) | F5: =IF(OR(A5="",E5=0),"",MAX(0,D5)/E5)
A6: =IF(Справочники!J7="","",Справочники!J7) | B6: =IF(A6="","",Справочники!K7) | D6: =IF(A6="","",B6-C6) | F6: =IF(OR(A6="",E6=0),"",MAX(0,D6)/E6)
A7: =IF(Справочники!J8="","",Справочники!J8) | B7: =IF(A7="","",Справочники!K8) | D7: =IF(A7="","",B7-C7) | F7: =IF(OR(A7="",E7=0),"",MAX(0,D7)/E7)
A8: =IF(Справочники!J9="","",Справочники!J9) | B8: =IF(A8="","",Справочники!K9) | D8: =IF(A8="","",B8-C8) | F8: =IF(OR(A8="",E8=0),"",MAX(0,D8)/E8)
A9: =IF(Справочники!J10="","",Справочники!J10) | B9: =IF(A9="","",Справочники!K10) | D9: =IF(A9="","",B9-C9) | F9: =IF(OR(A9="",E9=0),"",MAX(0,D9)/E9)
A10: =IF(Справочники!J11="","",Справочники!J11) | B10: =IF(A10="","",Справочники!K11) | D10: =IF(A10="","",B10-C10) | F10: =IF(OR(A10="",E10=0),"",MAX(0,D10)/E10)
A11: =IF(Справочники!J12="","",Справочники!J12) | B11: =IF(A11="","",Справочники!K12) | D11: =IF(A11="","",B11-C11) | F11: =IF(OR(A11="",E11=0),"",MAX(0,D11)/E11)
A12: =IF(Справочники!J13="","",Справочники!J13) | B12: =IF(A12="","",Справочники!K13) | D12: =IF(A12="","",B12-C12) | F12: =IF(OR(A12="",E12=0),"",MAX(0,D12)/E12)
A13: =IF(Справочники!J14="","",Справочники!J14) | B13: =IF(A13="","",Справочники!K14) | D13: =IF(A13="","",B13-C13) | F13: =IF(OR(A13="",E13=0),"",MAX(0,D13)/E13)
A14: =IF(Справочники!J15="","",Справочники!J15) | B14: =IF(A14="","",Справочники!K15) | D14: =IF(A14="","",B14-C14) | F14: =IF(OR(A14="",E14=0),"",MAX(0,D14)/E14)
A15: =IF(Справочники!J16="","",Справочники!J16) | B15: =IF(A15="","",Справочники!K16) | D15: =IF(A15="","",B15-C15) | F15: =IF(OR(A15="",E15=0),"",MAX(0,D15)/E15)
... A23: =IF(Справочники!J24="","",Справочники!J24) | B23: =IF(A23="","",Справочники!K24) | D23: =IF(A23="","",B23-C23) | F23: =IF(OR(A23="",E23=0),"",MAX(0,D23)/E23)

Sheet Цели
A1: Цели владельца
A3: Цель | B3: Тип | C3: План | D3: Факт | E3: Прогресс | F3: Осталось
E4: =IF(C4=0,"",D4/C4) | F4: =IF(C4="","",C4-D4)
E5: =IF(C5=0,"",D5/C5) | F5: =IF(C5="","",C5-D5)
E6: =IF(C6=0,"",D6/C6) | F6: =IF(C6="","",C6-D6)
E7: =IF(C7=0,"",D7/C7) | F7: =IF(C7="","",C7-D7)
E8: =IF(C8=0,"",D8/C8) | F8: =IF(C8="","",C8-D8)
E9: =IF(C9=0,"",D9/C9) | F9: =IF(C9="","",C9-D9)
E10: =IF(C10=0,"",D10/C10) | F10: =IF(C10="","",C10-D10)
E11: =IF(C11=0,"",D11/C11) | F11: =IF(C11="","",C11-D11)
E12: =IF(C12=0,"",D12/C12) | F12: =IF(C12="","",C12-D12)
E13: =IF(C13=0,"",D13/C13) | F13: =IF(C13="","",C13-D13)
E14: =IF(C14=0,"",D14/C14) | F14: =IF(C14="","",C14-D14)
E15: =IF(C15=0,"",D15/C15) | F15: =IF(C15="","",C15-D15)
... E23: =IF(C23=0,"",D23/C23) | F23: =IF(C23="","",C23-D23)

Sheet Расходы
A1: Прочие расходы и списания
A3: Дата | B3: Категория | C3: Сумма | D3: Комментарий

Sheet Отчёт
A1: Итог месяца
A2: Собирается автоматически из всех листов. Себестоимость впиши вручную для расчёта рентабельности.
A3: ВЫРУЧКА
A4: Наличные (Z) | B4: =SUM(Касса!D4:D203)
A5: Карта (Z) | B5: =SUM(Касса!E4:E203)
A6: Переводы СБП (Z) | B6: =SUM(Касса!F4:F203)
A7: Выручка всего | B7: =SUM(Касса!G4:G203) | C7: наличка + карта + СБП
A9: РАСХОДЫ
A10: Оплачено поставщикам | B10: =SUM(Выплаты!C4:C203) | C10: наличными
A11: Зарплата к выплате | B11: =Зарплата!F34 | C11: из табеля
A12: Накопления отложено | B12: =SUM(Накопления!C4:C23) | C12: аренда/зарплата/налоги
A13: Прочие расходы | B13: =SUM(Расходы!C4:C203)
A14: Расходы всего | B14: =B10+B11+B12+B13
A16: ИТОГИ
A17: Себестоимость проданного | B17: 0 | C17: впиши вручную или из 1С
A18: Валовая прибыль | B18: =B7-B17 | C18: выручка − себестоимость
A19: Рентабельность | B19: =IF(B7=0,"",B18/B7) | C19: цель: см. Справочники
A20: Долг поставщикам (конец) | B20: =Долги!E54
A21: Расхождения за месяц | B21: =SUM(Касса!J4:J203) | C21: сумма всех расхождений кассы
